pyhtml2md.cpython-39-x86_64-linux-gnu.so
pyhtml2md-1.7.0.dist-info/WHEEL
pyhtml2md-1.7.0.dist-info/METADATA
pyhtml2md-1.7.0.dist-info/RECORD
pyhtml2md-1.7.0.dist-info/licenses/COPYING
pyhtml2md.libs/libstdc++-496613c0.so.6.0.32
pyhtml2md.libs/libgcc_s-a3a07607.so.1
