Metadata-Version: 2.1
Name: pyhtml2md
Version: 1.7.0
Summary: Transform your HTML into clean, easy-to-read markdown with pyhtml2md.
Keywords: html,markdown,html-to-markdown,python3,cpp17,cpp-library,html2markdown,html2md
Author-Email: Tim Gromeyer <sakul8826@gmail.com>
License: MIT
Classifier: Intended Audience :: Developers
Classifier: License :: OSI Approved :: MIT License
Classifier: Programming Language :: C++
Classifier: Programming Language :: Python
Classifier: Programming Language :: Python :: 3
Classifier: Programming Language :: Python :: 3 :: Only
Classifier: Programming Language :: Python :: 3.7
Classifier: Programming Language :: Python :: 3.8
Classifier: Programming Language :: Python :: 3.9
Classifier: Topic :: File Formats
Classifier: Topic :: Text Processing :: Markup :: Markdown
Classifier: Topic :: Text Processing :: Markup :: HTML
Project-URL: Repository, https://github.com/tim-gromeyer/html2md
Requires-Python: >=3.7
Provides-Extra: test
Requires-Dist: pytest>=6.0; extra == "test"
